{
    "linkConfig": [
        {
            "type": "pktOptLink",
            "params": {
                "port2": 1,
                "port1": 2
            },
            "nodeDpid1": "00:00:00:00:00:00:00:01",
            "nodeDpid2": "00:00:00:00:00:00:00:11"
        },
        {
            "type": "pktOptLink",
            "params": {
                "port2": 1,
                "port1": 2
            },
            "nodeDpid1": "00:00:00:00:00:00:00:02",
            "nodeDpid2": "00:00:00:00:00:00:00:14"
        },
        {
            "type": "wdmLink",
            "params": {
                "port2": 1,
                "port1": 2
            },
            "nodeDpid1": "00:00:00:00:00:00:00:11",
            "nodeDpid2": "00:00:00:00:00:00:00:12"
        },
        {
            "type": "wdmLink",
            "params": {
                "port2": 1,
                "port1": 3
            },
            "nodeDpid1": "00:00:00:00:00:00:00:11",
            "nodeDpid2": "00:00:00:00:00:00:00:15"
        },
        {
            "type": "wdmLink",
            "params": {
                "port2": 1,
                "port1": 2
            },
            "nodeDpid1": "00:00:00:00:00:00:00:12",
            "nodeDpid2": "00:00:00:00:00:00:00:13"
        },
        {
            "type": "wdmLink",
            "params": {
                "port2": 2,
                "port1": 2
            },
            "nodeDpid1": "00:00:00:00:00:00:00:13",
            "nodeDpid2": "00:00:00:00:00:00:00:14"
        },
        {
            "type": "wdmLink",
            "params": {
                "port2": 3,
                "port1": 2
            },
            "nodeDpid1": "00:00:00:00:00:00:00:15",
            "nodeDpid2": "00:00:00:00:00:00:00:14"
        }
    ],
    "switchConfig": [
        {
            "nodeDpid": "00:00:00:00:00:00:00:11"
        },
        {
            "nodeDpid": "00:00:00:00:00:00:00:12"
        },
        {
            "nodeDpid": "00:00:00:00:00:00:00:13"
        },
        {
            "nodeDpid": "00:00:00:00:00:00:00:14"
        },
        {
            "nodeDpid": "00:00:00:00:00:00:00:15"
        }
    ]
}